structuremap/__init__.py
structuremap/cli.py
structuremap/gui.py
structuremap/plotting.py
structuremap/processing.py
structuremap/utils.py
structuremap/__pycache__/__init__.cpython-38.pyc
structuremap-0.0.10.dist-info/LICENSE.txt
structuremap-0.0.10.dist-info/METADATA
structuremap-0.0.10.dist-info/WHEEL
structuremap-0.0.10.dist-info/entry_points.txt
structuremap-0.0.10.dist-info/top_level.txt
structuremap-0.0.10.dist-info/RECORD
