Metadata-Version: 2.1
Name: structuremap
Version: 0.0.10
Summary: An open-source Python package of the AlphaPept ecosystem
Home-page: https://github.com/MannLabs/structuremap
Author: Isabell Bludau & Mann Labs
Author-email: opensource@alphapept.com
License: Apache
Project-URL: Mann Labs at MPIB, https://www.biochem.mpg.de/mann
Project-URL: Mann Labs at CPR, https://www.cpr.ku.dk/research/proteomics/mann/
Project-URL: GitHub, https://github.com/MannLabs/structuremap
Keywords: bioinformatics,software,AlphaPept ecosystem
Classifier: Development Status :: 1 - Planning
Classifier: Intended Audience :: Science/Research
Classifier: License :: OSI Approved :: Apache Software License
Classifier: Operating System :: OS Independent
Classifier: Programming Language :: Python :: 3
Classifier: Topic :: Scientific/Engineering :: Bio-Informatics
Requires-Python: >=3.8
License-File: LICENSE.txt
Requires-Dist: click
Requires-Dist: numba
Requires-Dist: pandas
Requires-Dist: tqdm
Requires-Dist: h5py
Requires-Dist: statsmodels
Requires-Dist: bio
Requires-Dist: plotly
Requires-Dist: pywin32==225; sys_platform == "win32"
Provides-Extra: development
Requires-Dist: jupyter; extra == "development"
Requires-Dist: jupyter-contrib-nbextensions; extra == "development"
Requires-Dist: pyinstaller; extra == "development"
Requires-Dist: autodocsumm; extra == "development"
Requires-Dist: sphinx-rtd-theme; extra == "development"
Requires-Dist: twine; extra == "development"
Requires-Dist: bumpversion; extra == "development"
Requires-Dist: pipdeptree; extra == "development"
Requires-Dist: psutil; extra == "development"
Requires-Dist: notebook; extra == "development"
Provides-Extra: development-stable
Requires-Dist: jupyter==1.0.0; extra == "development-stable"
Requires-Dist: jupyter-contrib-nbextensions==0.5.1; extra == "development-stable"
Requires-Dist: pyinstaller==6.3.0; extra == "development-stable"
Requires-Dist: autodocsumm==0.2.6; extra == "development-stable"
Requires-Dist: sphinx-rtd-theme==0.5.2; extra == "development-stable"
Requires-Dist: twine==3.4.1; extra == "development-stable"
Requires-Dist: bumpversion==0.6.0; extra == "development-stable"
Requires-Dist: pipdeptree==2.1.0; extra == "development-stable"
Requires-Dist: psutil==5.8.0; extra == "development-stable"
Requires-Dist: notebook==6.4.12; extra == "development-stable"
Provides-Extra: stable
Requires-Dist: click==8.0.1; extra == "stable"
Requires-Dist: numba==0.55.1; extra == "stable"
Requires-Dist: pandas==1.4.0; extra == "stable"
Requires-Dist: tqdm==4.62.3; extra == "stable"
Requires-Dist: h5py==3.6.0; extra == "stable"
Requires-Dist: statsmodels==0.13.1; extra == "stable"
Requires-Dist: bio==1.3.3; extra == "stable"
Requires-Dist: plotly==4.12.0; extra == "stable"
